experimentkit/__init__.py
experimentkit/_config.py
experimentkit/environment.py
experimentkit/evaluation/__init__.py
experimentkit/evaluation/regression.py
experimentkit/funx.py
experimentkit/generators/__init__.py
experimentkit/generators/time_series.py
experimentkit/logger_config.py
experimentkit/metricsreport.py
experimentkit/monitor.py
experimentkit/reporting.py
experimentkit/study_setup/__init__.py
experimentkit/study_setup/project_structures.py
experimentkit/study_setup/study_setup.py
experimentkit/visualization.py
experimentkit-0.1.20.dist-info/LICENSE
experimentkit-0.1.20.dist-info/METADATA
experimentkit-0.1.20.dist-info/WHEEL
experimentkit-0.1.20.dist-info/RECORD
