Metadata-Version: 2.1
Name: experimentkit
Version: 0.1.20
Summary: A toolkit for easily running research experiments
Author: gianfa
Author-email: gian.angelini@hotmail.com
Requires-Python: >=3.9,<4.0
Classifier: Programming Language :: Python :: 3
Classifier: Programming Language :: Python :: 3.9
Classifier: Programming Language :: Python :: 3.10
Classifier: Programming Language :: Python :: 3.11
Classifier: Programming Language :: Python :: 3.12
Requires-Dist: jupyter (>=1.0.0,<2.0.0)
Requires-Dist: latex (>=0.7.0,<0.8.0)
Requires-Dist: matplotlib (>=3.5.3,<4.0.0)
Requires-Dist: numpy (>=1.23.2,<2.0.0)
Requires-Dist: pandas (>=1.4.4,<2.0.0)
Requires-Dist: scienceplots (==2.1.1)
Requires-Dist: scikit-learn (>=1.2.1,<2.0.0)
Requires-Dist: scipy (>=1.3,<1.9)
Requires-Dist: seaborn (==0.12.0)
Requires-Dist: statsmodels (>=0.13.5,<0.14.0)
Requires-Dist: toml (>=0.10.2,<0.11.0)
